gitfarts/__init__.py
gitfarts/main.py
gitfarts-0.1.2.dist-info/METADATA
gitfarts-0.1.2.dist-info/WHEEL
gitfarts-0.1.2.dist-info/entry_points.txt
gitfarts-0.1.2.dist-info/RECORD
